relife/__init__.py
relife/base.py
relife/conftest.py
relife/economic.py
relife/data/__init__.py
relife/data/dataset.py
relife/data/nhpp_data.py
relife/data/csv/__init__.py
relife/data/csv/circuit_breaker.csv
relife/data/csv/input_turnbull.csv
relife/data/csv/insulator_string.csv
relife/data/csv/power_transformer.csv
relife/data/tests/__init__.py
relife/data/tests/test_nhpp_data.py
relife/lifetime_model/__init__.py
relife/lifetime_model/_base.py
relife/lifetime_model/_conditional_model.py
relife/lifetime_model/_distribution.py
relife/lifetime_model/_frozen.py
relife/lifetime_model/_non_parametric.py
relife/lifetime_model/_plot.py
relife/lifetime_model/_regression.py
relife/lifetime_model/tests/__init__.py
relife/lifetime_model/tests/test_conditional_model.py
relife/lifetime_model/tests/test_distribution.py
relife/lifetime_model/tests/test_frozen_model.py
relife/lifetime_model/tests/test_regression.py
relife/likelihood/__init__.py
relife/likelihood/_base.py
relife/likelihood/_lifetime_likelihood.py
relife/likelihood/tests/__init__.py
relife/likelihood/tests/test_default_lifetime_likelihood.py
relife/policy/__init__.py
relife/policy/_base.py
relife/policy/_preventive_age_replacement.py
relife/policy/_run_to_failure.py
relife/policy/tests/__init__.py
relife/policy/tests/test_age_replacement_policy.py
relife/policy/tests/test_run_to_failure_policy.py
relife/stochastic_process/__init__.py
relife/stochastic_process/_renewal_equations.py
relife/stochastic_process/non_homogeneous_poisson_process.py
relife/stochastic_process/renewal_process.py
relife/stochastic_process/_sample/__init__.py
relife/stochastic_process/_sample/data.py
relife/stochastic_process/_sample/iterables.py
relife/stochastic_process/_sample/iterators.py
relife/stochastic_process/tests/__init__.py
relife/stochastic_process/tests/test_renewal_process.py
relife/tests/__init__.py
relife/tests/test_economic.py
relife/tests/test_parametric_model.py
relife/tests/test_quadrature.py
relife/typing/__init__.py
relife-2.3.1.dist-info/licenses/LICENSE.txt
relife-2.3.1.dist-info/METADATA
relife-2.3.1.dist-info/WHEEL
relife-2.3.1.dist-info/top_level.txt
relife-2.3.1.dist-info/RECORD
