Metadata-Version: 2.4
Name: relife
Version: 2.3.1
Summary: ReLife is an open source Python library for asset management based on reliability theory.
Author-email: Thomas Guillon <thomas.guillon@rte-france.com>
Maintainer-email: William Grison <william.grison@rte-france.com>
License-Expression: Apache-2.0
Project-URL: Homepage, https://github.com/rte-france/relife
Project-URL: Documentation, http://opensource.rte-france.com/relife/
Project-URL: Issues, https://github.com/rte-france/relife/issues
Classifier: Programming Language :: Python :: 3
Classifier: Operating System :: OS Independent
Requires-Python: >=3.11
License-File: LICENSE.txt
Requires-Dist: numpy>=2.2.0
Requires-Dist: scipy>=1.15.0
Requires-Dist: matplotlib>=3.10.0
Requires-Dist: typing_extensions>=4.12.2
Provides-Extra: dev
Requires-Dist: pytest>=8.3.0; extra == "dev"
Requires-Dist: isort>=6.0.0; extra == "dev"
Requires-Dist: black>=25.1.0; extra == "dev"
Requires-Dist: mypy>=1.15.0; extra == "dev"
Requires-Dist: mypy-extensions>=1.0.0; extra == "dev"
Requires-Dist: no-implicit-optional; extra == "dev"
Requires-Dist: scipy-stubs; extra == "dev"
Requires-Dist: Sphinx>=8.1.3; extra == "dev"
Requires-Dist: pydata-sphinx-theme>=0.16.1; extra == "dev"
Requires-Dist: sphinx-copybutton>=0.5.2; extra == "dev"
Requires-Dist: sphinx_design>=0.6.1; extra == "dev"
Requires-Dist: numpydoc>=1.8.0; extra == "dev"
Requires-Dist: nbsphinx>=0.9.7; extra == "dev"
Requires-Dist: myst-parser>=4.0.1; extra == "dev"
Requires-Dist: jupyterlab>=4.3.5; extra == "dev"
Requires-Dist: setuptools-scm>=8.0.0; extra == "dev"
Requires-Dist: pylint>=4.0.4; extra == "dev"
Requires-Dist: flake8>=7.3.0; extra == "dev"
Requires-Dist: pyright>=1.1.408; extra == "dev"
Dynamic: license-file
